pyMate/Clyde.py
pyMate/Gordo.py
pyMate/Zaius.py
pyMate/__init__.py
real_pymate-1.0.3.dist-info/LICENSE
real_pymate-1.0.3.dist-info/METADATA
real_pymate-1.0.3.dist-info/WHEEL
real_pymate-1.0.3.dist-info/top_level.txt
real_pymate-1.0.3.dist-info/RECORD
