Metadata-Version: 2.1
Name: real_pymate
Version: 1.0.3
Summary: Framework to process primate fMRI and electrophysiological data
Home-page: https://github.com/akcarsten/pyMate
Author: Carsten Klein
Classifier: Programming Language :: Python :: 3
Classifier: License :: OSI Approved :: MIT License
Classifier: Operating System :: OS Independent
License-File: LICENSE
